<?xml version="1.0" encoding="UTF-8"?>
<sv:node sv:name="howTo" xmlns:sv="http://www.jcp.org/jcr/sv/1.0" xmlns:xsi="http://www.w3.org/2001/XMLSchema-instance">
  <sv:property sv:name="jcr:primaryType" sv:type="Name">
    <sv:value>mgnl:contentNode</sv:value>
  </sv:property>
  <sv:property sv:name="jcr:mixinTypes" sv:type="Name" sv:multiple="true">
    <sv:value>mix:lockable</sv:value>
  </sv:property>
  <sv:property sv:name="jcr:uuid" sv:type="String">
    <sv:value>6e4e9cb5-5d16-4fdf-892a-7c6e64811590</sv:value>
  </sv:property>
  <sv:property sv:name="jcr:createdBy" sv:type="String">
    <sv:value>admin</sv:value>
  </sv:property>
  <sv:node sv:name="MetaData">
    <sv:property sv:name="jcr:primaryType" sv:type="Name">
      <sv:value>mgnl:metaData</sv:value>
    </sv:property>
    <sv:property sv:name="jcr:createdBy" sv:type="String">
      <sv:value>admin</sv:value>
    </sv:property>
    <sv:property sv:name="mgnl:authorid" sv:type="String">
      <sv:value>superuser</sv:value>
    </sv:property>
    <sv:property sv:name="mgnl:creationdate" sv:type="Date">
      <sv:value>2011-06-13T11:55:08.123+02:00</sv:value>
    </sv:property>
    <sv:property sv:name="mgnl:lastmodified" sv:type="Date">
      <sv:value>2011-06-13T11:55:13.804+02:00</sv:value>
    </sv:property>
  </sv:node>
  <sv:node sv:name="tabs">
    <sv:property sv:name="jcr:primaryType" sv:type="Name">
      <sv:value>mgnl:contentNode</sv:value>
    </sv:property>
    <sv:property sv:name="jcr:mixinTypes" sv:type="Name" sv:multiple="true">
      <sv:value>mix:lockable</sv:value>
    </sv:property>
    <sv:property sv:name="jcr:uuid" sv:type="String">
      <sv:value>09619af0-fb4f-4a74-b025-00adc0392132</sv:value>
    </sv:property>
    <sv:property sv:name="jcr:createdBy" sv:type="String">
      <sv:value>admin</sv:value>
    </sv:property>
    <sv:node sv:name="MetaData">
      <sv:property sv:name="jcr:primaryType" sv:type="Name">
        <sv:value>mgnl:metaData</sv:value>
      </sv:property>
      <sv:property sv:name="jcr:createdBy" sv:type="String">
        <sv:value>admin</sv:value>
      </sv:property>
      <sv:property sv:name="mgnl:authorid" sv:type="String">
        <sv:value>superuser</sv:value>
      </sv:property>
      <sv:property sv:name="mgnl:creationdate" sv:type="Date">
        <sv:value>2011-06-13T11:55:21.155+02:00</sv:value>
      </sv:property>
      <sv:property sv:name="mgnl:lastmodified" sv:type="Date">
        <sv:value>2011-06-13T11:55:25.527+02:00</sv:value>
      </sv:property>
    </sv:node>
    <sv:node sv:name="tabMain">
      <sv:property sv:name="jcr:primaryType" sv:type="Name">
        <sv:value>mgnl:contentNode</sv:value>
      </sv:property>
      <sv:property sv:name="jcr:mixinTypes" sv:type="Name" sv:multiple="true">
        <sv:value>mix:lockable</sv:value>
      </sv:property>
      <sv:property sv:name="jcr:uuid" sv:type="String">
        <sv:value>c943bdfd-bce3-4463-a3d3-9882d082112f</sv:value>
      </sv:property>
      <sv:property sv:name="jcr:createdBy" sv:type="String">
        <sv:value>admin</sv:value>
      </sv:property>
      <sv:property sv:name="label" sv:type="String">
        <sv:value>Settings</sv:value>
      </sv:property>
      <sv:node sv:name="MetaData">
        <sv:property sv:name="jcr:primaryType" sv:type="Name">
          <sv:value>mgnl:metaData</sv:value>
        </sv:property>
        <sv:property sv:name="jcr:createdBy" sv:type="String">
          <sv:value>admin</sv:value>
        </sv:property>
        <sv:property sv:name="mgnl:authorid" sv:type="String">
          <sv:value>superuser</sv:value>
        </sv:property>
        <sv:property sv:name="mgnl:creationdate" sv:type="Date">
          <sv:value>2011-06-13T11:55:33.937+02:00</sv:value>
        </sv:property>
        <sv:property sv:name="mgnl:lastmodified" sv:type="Date">
          <sv:value>2011-06-13T11:55:56.134+02:00</sv:value>
        </sv:property>
      </sv:node>
      <sv:node sv:name="title">
        <sv:property sv:name="jcr:primaryType" sv:type="Name">
          <sv:value>mgnl:contentNode</sv:value>
        </sv:property>
        <sv:property sv:name="jcr:mixinTypes" sv:type="Name" sv:multiple="true">
          <sv:value>mix:lockable</sv:value>
        </sv:property>
        <sv:property sv:name="jcr:uuid" sv:type="String">
          <sv:value>45fa5524-fafb-4e58-a1cb-047dc59193b7</sv:value>
        </sv:property>
        <sv:property sv:name="class" sv:type="String">
          <sv:value>info.magnolia.ui.model.dialog.definition.EditFieldDefinition</sv:value>
        </sv:property>
        <sv:property sv:name="description" sv:type="String">
          <sv:value/>
        </sv:property>
        <sv:property sv:name="jcr:createdBy" sv:type="String">
          <sv:value>admin</sv:value>
        </sv:property>
        <sv:property sv:name="label" sv:type="String">
          <sv:value>dialog.sampleProperties.title</sv:value>
        </sv:property>
        <sv:node sv:name="MetaData">
          <sv:property sv:name="jcr:primaryType" sv:type="Name">
            <sv:value>mgnl:metaData</sv:value>
          </sv:property>
          <sv:property sv:name="jcr:createdBy" sv:type="String">
            <sv:value>admin</sv:value>
          </sv:property>
          <sv:property sv:name="mgnl:activated" sv:type="Boolean">
            <sv:value>false</sv:value>
          </sv:property>
          <sv:property sv:name="mgnl:authorid" sv:type="String">
            <sv:value>superuser</sv:value>
          </sv:property>
          <sv:property sv:name="mgnl:creationdate" sv:type="Date">
            <sv:value>2008-09-25T13:57:00.582+02:00</sv:value>
          </sv:property>
          <sv:property sv:name="mgnl:lastmodified" sv:type="Date">
            <sv:value>2011-06-13T11:57:02.247+02:00</sv:value>
          </sv:property>
        </sv:node>
      </sv:node>
      <sv:node sv:name="text">
        <sv:property sv:name="jcr:primaryType" sv:type="Name">
          <sv:value>mgnl:contentNode</sv:value>
        </sv:property>
        <sv:property sv:name="jcr:mixinTypes" sv:type="Name" sv:multiple="true">
          <sv:value>mix:lockable</sv:value>
        </sv:property>
        <sv:property sv:name="jcr:uuid" sv:type="String">
          <sv:value>5bf50b4b-5e25-4c58-a95b-75d3a34b49cb</sv:value>
        </sv:property>
        <sv:property sv:name="class" sv:type="String">
          <sv:value>info.magnolia.ckeditor.dialog.definition.CKEditorFieldDefinition</sv:value>
        </sv:property>
        <sv:property sv:name="description" sv:type="String">
          <sv:value>dialog.sampleProperties.description</sv:value>
        </sv:property>
        <sv:property sv:name="jcr:createdBy" sv:type="String">
          <sv:value>admin</sv:value>
        </sv:property>
        <sv:property sv:name="label" sv:type="String">
          <sv:value>dialog.sampleProperties.text</sv:value>
        </sv:property>
        <sv:node sv:name="MetaData">
          <sv:property sv:name="jcr:primaryType" sv:type="Name">
            <sv:value>mgnl:metaData</sv:value>
          </sv:property>
          <sv:property sv:name="jcr:createdBy" sv:type="String">
            <sv:value>admin</sv:value>
          </sv:property>
          <sv:property sv:name="mgnl:activated" sv:type="Boolean">
            <sv:value>false</sv:value>
          </sv:property>
          <sv:property sv:name="mgnl:authorid" sv:type="String">
            <sv:value>superuser</sv:value>
          </sv:property>
          <sv:property sv:name="mgnl:creationdate" sv:type="Date">
            <sv:value>2008-09-25T13:57:00.582+02:00</sv:value>
          </sv:property>
          <sv:property sv:name="mgnl:lastmodified" sv:type="Date">
            <sv:value>2011-06-13T11:57:07.058+02:00</sv:value>
          </sv:property>
        </sv:node>
      </sv:node>
      <sv:node sv:name="date">
        <sv:property sv:name="jcr:primaryType" sv:type="Name">
          <sv:value>mgnl:contentNode</sv:value>
        </sv:property>
        <sv:property sv:name="jcr:mixinTypes" sv:type="Name" sv:multiple="true">
          <sv:value>mix:lockable</sv:value>
        </sv:property>
        <sv:property sv:name="jcr:uuid" sv:type="String">
          <sv:value>582f4b90-eaed-448f-b258-5f277e9d5bbe</sv:value>
        </sv:property>
        <sv:property sv:name="class" sv:type="String">
          <sv:value>info.magnolia.ui.model.dialog.definition.DateFieldDefinition</sv:value>
        </sv:property>
        <sv:property sv:name="description" sv:type="String">
          <sv:value/>
        </sv:property>
        <sv:property sv:name="jcr:createdBy" sv:type="String">
          <sv:value>admin</sv:value>
        </sv:property>
        <sv:property sv:name="label" sv:type="String">
          <sv:value>Date</sv:value>
        </sv:property>
        <sv:property sv:name="type" sv:type="String">
          <sv:value>Date</sv:value>
        </sv:property>
        <sv:node sv:name="MetaData">
          <sv:property sv:name="jcr:primaryType" sv:type="Name">
            <sv:value>mgnl:metaData</sv:value>
          </sv:property>
          <sv:property sv:name="jcr:createdBy" sv:type="String">
            <sv:value>admin</sv:value>
          </sv:property>
          <sv:property sv:name="mgnl:activated" sv:type="Boolean">
            <sv:value>false</sv:value>
          </sv:property>
          <sv:property sv:name="mgnl:authorid" sv:type="String">
            <sv:value>superuser</sv:value>
          </sv:property>
          <sv:property sv:name="mgnl:creationdate" sv:type="Date">
            <sv:value>2011-05-31T14:14:05.903+02:00</sv:value>
          </sv:property>
          <sv:property sv:name="mgnl:lastmodified" sv:type="Date">
            <sv:value>2011-06-13T11:58:15.397+02:00</sv:value>
          </sv:property>
        </sv:node>
      </sv:node>
      <sv:node sv:name="image">
        <sv:property sv:name="jcr:primaryType" sv:type="Name">
          <sv:value>mgnl:contentNode</sv:value>
        </sv:property>
        <sv:property sv:name="jcr:mixinTypes" sv:type="Name" sv:multiple="true">
          <sv:value>mix:lockable</sv:value>
        </sv:property>
        <sv:property sv:name="jcr:uuid" sv:type="String">
          <sv:value>80404d65-3386-4b5d-ba42-e0569e489aa2</sv:value>
        </sv:property>
        <sv:property sv:name="class" sv:type="String">
          <sv:value>info.magnolia.ui.model.dialog.definition.FileUploadFieldDefinition</sv:value>
        </sv:property>
        <sv:property sv:name="jcr:createdBy" sv:type="String">
          <sv:value>admin</sv:value>
        </sv:property>
        <sv:property sv:name="label" sv:type="String">
          <sv:value>Image</sv:value>
        </sv:property>
        <sv:node sv:name="MetaData">
          <sv:property sv:name="jcr:primaryType" sv:type="Name">
            <sv:value>mgnl:metaData</sv:value>
          </sv:property>
          <sv:property sv:name="jcr:createdBy" sv:type="String">
            <sv:value>admin</sv:value>
          </sv:property>
          <sv:property sv:name="mgnl:activated" sv:type="Boolean">
            <sv:value>false</sv:value>
          </sv:property>
          <sv:property sv:name="mgnl:authorid" sv:type="String">
            <sv:value>superuser</sv:value>
          </sv:property>
          <sv:property sv:name="mgnl:creationdate" sv:type="Date">
            <sv:value>2011-06-01T15:16:27.248+02:00</sv:value>
          </sv:property>
          <sv:property sv:name="mgnl:lastmodified" sv:type="Date">
            <sv:value>2011-06-13T11:58:10.200+02:00</sv:value>
          </sv:property>
        </sv:node>
      </sv:node>
    </sv:node>
  </sv:node>
</sv:node>
