<?xml version="1.0" encoding="UTF-8"?>
<sv:node sv:name="howTo" xmlns:sv="http://www.jcp.org/jcr/sv/1.0" xmlns:xsi="http://www.w3.org/2001/XMLSchema-instance">
  <sv:property sv:name="jcr:primaryType" sv:type="Name">
    <sv:value>mgnl:contentNode</sv:value>
  </sv:property>
  <sv:property sv:name="jcr:mixinTypes" sv:type="Name" sv:multiple="true">
    <sv:value>mix:lockable</sv:value>
  </sv:property>
  <sv:property sv:name="jcr:uuid" sv:type="String">
    <sv:value>6e4e9cb5-5d16-4fdf-892a-7c6e64811590</sv:value>
  </sv:property>
  <sv:property sv:name="jcr:createdBy" sv:type="String">
    <sv:value>admin</sv:value>
  </sv:property>
  <sv:node sv:name="MetaData">
    <sv:property sv:name="jcr:primaryType" sv:type="Name">
      <sv:value>mgnl:metaData</sv:value>
    </sv:property>
    <sv:property sv:name="jcr:createdBy" sv:type="String">
      <sv:value>admin</sv:value>
    </sv:property>
    <sv:property sv:name="mgnl:authorid" sv:type="String">
      <sv:value>superuser</sv:value>
    </sv:property>
    <sv:property sv:name="mgnl:creationdate" sv:type="Date">
      <sv:value>2011-06-13T11:55:08.123+02:00</sv:value>
    </sv:property>
    <sv:property sv:name="mgnl:lastmodified" sv:type="Date">
      <sv:value>2011-06-13T11:55:13.804+02:00</sv:value>
    </sv:property>
  </sv:node>
  <sv:node sv:name="tabMain">
    <sv:property sv:name="jcr:primaryType" sv:type="Name">
      <sv:value>mgnl:contentNode</sv:value>
    </sv:property>
    <sv:property sv:name="jcr:mixinTypes" sv:type="Name" sv:multiple="true">
      <sv:value>mix:lockable</sv:value>
    </sv:property>
    <sv:property sv:name="jcr:uuid" sv:type="String">
      <sv:value>d2ead2f8-9768-48bc-867b-8f9de5d89738</sv:value>
    </sv:property>
    <sv:property sv:name="controlType" sv:type="String">
      <sv:value>tab</sv:value>
    </sv:property>
    <sv:property sv:name="jcr:createdBy" sv:type="String">
      <sv:value>admin</sv:value>
    </sv:property>
    <sv:property sv:name="label" sv:type="String">
      <sv:value>Settings</sv:value>
    </sv:property>
    <sv:node sv:name="MetaData">
      <sv:property sv:name="jcr:primaryType" sv:type="Name">
        <sv:value>mgnl:metaData</sv:value>
      </sv:property>
      <sv:property sv:name="jcr:createdBy" sv:type="String">
        <sv:value>admin</sv:value>
      </sv:property>
      <sv:property sv:name="mgnl:activated" sv:type="Boolean">
        <sv:value>false</sv:value>
      </sv:property>
      <sv:property sv:name="mgnl:authorid" sv:type="String">
        <sv:value>superuser</sv:value>
      </sv:property>
      <sv:property sv:name="mgnl:creationdate" sv:type="Date">
        <sv:value>2008-10-10T14:53:55.191+02:00</sv:value>
      </sv:property>
      <sv:property sv:name="mgnl:lastmodified" sv:type="Date">
        <sv:value>2011-08-24T16:20:35.224+02:00</sv:value>
      </sv:property>
    </sv:node>
    <sv:node sv:name="title">
      <sv:property sv:name="jcr:primaryType" sv:type="Name">
        <sv:value>mgnl:contentNode</sv:value>
      </sv:property>
      <sv:property sv:name="jcr:mixinTypes" sv:type="Name" sv:multiple="true">
        <sv:value>mix:lockable</sv:value>
      </sv:property>
      <sv:property sv:name="jcr:uuid" sv:type="String">
        <sv:value>f4766675-a5ce-4546-baae-aa7ef79492c0</sv:value>
      </sv:property>
      <sv:property sv:name="controlType" sv:type="String">
        <sv:value>edit</sv:value>
      </sv:property>
      <sv:property sv:name="description" sv:type="String">
        <sv:value/>
      </sv:property>
      <sv:property sv:name="jcr:createdBy" sv:type="String">
        <sv:value>admin</sv:value>
      </sv:property>
      <sv:property sv:name="label" sv:type="String">
        <sv:value>dialog.sampleProperties.title</sv:value>
      </sv:property>
      <sv:node sv:name="MetaData">
        <sv:property sv:name="jcr:primaryType" sv:type="Name">
          <sv:value>mgnl:metaData</sv:value>
        </sv:property>
        <sv:property sv:name="jcr:createdBy" sv:type="String">
          <sv:value>admin</sv:value>
        </sv:property>
        <sv:property sv:name="mgnl:activated" sv:type="Boolean">
          <sv:value>false</sv:value>
        </sv:property>
        <sv:property sv:name="mgnl:authorid" sv:type="String">
          <sv:value>superuser</sv:value>
        </sv:property>
        <sv:property sv:name="mgnl:creationdate" sv:type="Date">
          <sv:value>2008-09-25T13:57:00.582+02:00</sv:value>
        </sv:property>
        <sv:property sv:name="mgnl:lastmodified" sv:type="Date">
          <sv:value>2011-08-24T16:26:00.345+02:00</sv:value>
        </sv:property>
      </sv:node>
    </sv:node>
    <sv:node sv:name="text">
      <sv:property sv:name="jcr:primaryType" sv:type="Name">
        <sv:value>mgnl:contentNode</sv:value>
      </sv:property>
      <sv:property sv:name="jcr:mixinTypes" sv:type="Name" sv:multiple="true">
        <sv:value>mix:lockable</sv:value>
      </sv:property>
      <sv:property sv:name="jcr:uuid" sv:type="String">
        <sv:value>7468e6c9-3845-4436-9584-3365a89fbc5b</sv:value>
      </sv:property>
      <sv:property sv:name="controlType" sv:type="String">
        <sv:value>fckEdit</sv:value>
      </sv:property>
      <sv:property sv:name="description" sv:type="String">
        <sv:value>Introduce some formatted text</sv:value>
      </sv:property>
      <sv:property sv:name="jcr:createdBy" sv:type="String">
        <sv:value>admin</sv:value>
      </sv:property>
      <sv:property sv:name="label" sv:type="String">
        <sv:value>dialog.sampleProperties.text</sv:value>
      </sv:property>
      <sv:node sv:name="MetaData">
        <sv:property sv:name="jcr:primaryType" sv:type="Name">
          <sv:value>mgnl:metaData</sv:value>
        </sv:property>
        <sv:property sv:name="jcr:createdBy" sv:type="String">
          <sv:value>admin</sv:value>
        </sv:property>
        <sv:property sv:name="mgnl:activated" sv:type="Boolean">
          <sv:value>false</sv:value>
        </sv:property>
        <sv:property sv:name="mgnl:authorid" sv:type="String">
          <sv:value>superuser</sv:value>
        </sv:property>
        <sv:property sv:name="mgnl:creationdate" sv:type="Date">
          <sv:value>2008-09-25T13:57:00.582+02:00</sv:value>
        </sv:property>
        <sv:property sv:name="mgnl:lastmodified" sv:type="Date">
          <sv:value>2011-08-24T16:26:09.665+02:00</sv:value>
        </sv:property>
      </sv:node>
    </sv:node>
    <sv:node sv:name="image">
      <sv:property sv:name="jcr:primaryType" sv:type="Name">
        <sv:value>mgnl:contentNode</sv:value>
      </sv:property>
      <sv:property sv:name="jcr:mixinTypes" sv:type="Name" sv:multiple="true">
        <sv:value>mix:lockable</sv:value>
      </sv:property>
      <sv:property sv:name="jcr:uuid" sv:type="String">
        <sv:value>90905bf5-cb48-4539-b483-51b12a505b14</sv:value>
      </sv:property>
      <sv:property sv:name="controlType" sv:type="String">
        <sv:value>file</sv:value>
      </sv:property>
      <sv:property sv:name="description" sv:type="String">
        <sv:value/>
      </sv:property>
      <sv:property sv:name="jcr:createdBy" sv:type="String">
        <sv:value>admin</sv:value>
      </sv:property>
      <sv:property sv:name="label" sv:type="String">
        <sv:value>dialog.sampleProperties.image</sv:value>
      </sv:property>
      <sv:property sv:name="type" sv:type="String">
        <sv:value>Binary</sv:value>
      </sv:property>
      <sv:node sv:name="MetaData">
        <sv:property sv:name="jcr:primaryType" sv:type="Name">
          <sv:value>mgnl:metaData</sv:value>
        </sv:property>
        <sv:property sv:name="jcr:createdBy" sv:type="String">
          <sv:value>admin</sv:value>
        </sv:property>
        <sv:property sv:name="mgnl:activated" sv:type="Boolean">
          <sv:value>false</sv:value>
        </sv:property>
        <sv:property sv:name="mgnl:authorid" sv:type="String">
          <sv:value>superuser</sv:value>
        </sv:property>
        <sv:property sv:name="mgnl:creationdate" sv:type="Date">
          <sv:value>2008-09-25T13:57:00.582+02:00</sv:value>
        </sv:property>
        <sv:property sv:name="mgnl:lastmodified" sv:type="Date">
          <sv:value>2011-08-24T16:26:22.172+02:00</sv:value>
        </sv:property>
      </sv:node>
    </sv:node>
    <sv:node sv:name="date">
      <sv:property sv:name="jcr:primaryType" sv:type="Name">
        <sv:value>mgnl:contentNode</sv:value>
      </sv:property>
      <sv:property sv:name="jcr:mixinTypes" sv:type="Name" sv:multiple="true">
        <sv:value>mix:lockable</sv:value>
      </sv:property>
      <sv:property sv:name="jcr:uuid" sv:type="String">
        <sv:value>6c883e25-e86b-450b-9220-f841ace809dd</sv:value>
      </sv:property>
      <sv:property sv:name="controlType" sv:type="String">
        <sv:value>date</sv:value>
      </sv:property>
      <sv:property sv:name="description" sv:type="String">
        <sv:value/>
      </sv:property>
      <sv:property sv:name="jcr:createdBy" sv:type="String">
        <sv:value>admin</sv:value>
      </sv:property>
      <sv:property sv:name="label" sv:type="String">
        <sv:value>dialog.sampleProperties.date</sv:value>
      </sv:property>
      <sv:property sv:name="type" sv:type="String">
        <sv:value>Date</sv:value>
      </sv:property>
      <sv:node sv:name="MetaData">
        <sv:property sv:name="jcr:primaryType" sv:type="Name">
          <sv:value>mgnl:metaData</sv:value>
        </sv:property>
        <sv:property sv:name="jcr:createdBy" sv:type="String">
          <sv:value>admin</sv:value>
        </sv:property>
        <sv:property sv:name="mgnl:activated" sv:type="Boolean">
          <sv:value>false</sv:value>
        </sv:property>
        <sv:property sv:name="mgnl:authorid" sv:type="String">
          <sv:value>superuser</sv:value>
        </sv:property>
        <sv:property sv:name="mgnl:creationdate" sv:type="Date">
          <sv:value>2008-09-25T13:57:00.582+02:00</sv:value>
        </sv:property>
        <sv:property sv:name="mgnl:lastmodified" sv:type="Date">
          <sv:value>2011-10-14T12:09:16.461+02:00</sv:value>
        </sv:property>
      </sv:node>
    </sv:node>
  </sv:node>
</sv:node>
