<?xml version="1.0" encoding="UTF-8"?>
<sv:node sv:name="samples-devshow-include" xmlns:jcr="http://www.jcp.org/jcr/1.0"
  xmlns:mgnl="http://www.magnolia.info/jcr/mgnl" xmlns:rep="internal" xmlns:mix="http://www.jcp.org/jcr/mix/1.0"
  xmlns:nt="http://www.jcp.org/jcr/nt/1.0" xmlns:fn="http://www.w3.org/2005/xpath-functions"
  xmlns:xs="http://www.w3.org/2001/XMLSchema" xmlns:fn_old="http://www.w3.org/2004/10/xpath-functions"
  xmlns:sv="http://www.jcp.org/jcr/sv/1.0" xmlns:jcrfn="http://www.jcp.org/jcr/xpath-functions/1.0">
  <sv:property sv:name="jcr:primaryType" sv:type="Name">
    <sv:value>mgnl:content</sv:value>
  </sv:property>
  <sv:property sv:name="jcr:mixinTypes" sv:type="Name">
    <sv:value>mix:versionable</sv:value>
  </sv:property>
  <sv:property sv:name="jcr:uuid" sv:type="String">
    <sv:value>e34367bc-7cdd-427a-909e-2d675da4c672</sv:value>
  </sv:property>
  <sv:node sv:name="MetaData">
    <sv:property sv:name="jcr:primaryType" sv:type="Name">
      <sv:value>mgnl:metaData</sv:value>
    </sv:property>
    <sv:property sv:name="mgnl:authorid" sv:type="String">
      <sv:value>superuser</sv:value>
    </sv:property>
    <sv:property sv:name="mgnl:title" sv:type="String">
      <sv:value/>
    </sv:property>
    <sv:property sv:name="mgnl:creationdate" sv:type="String">
      <sv:value>2004-11-02T15:34:29.474+01:00</sv:value>
    </sv:property>
    <sv:property sv:name="mgnl:lastaction" sv:type="Date">
      <sv:value>2006-05-01T21:46:25.677+02:00</sv:value>
    </sv:property>
    <sv:property sv:name="mgnl:lastmodified" sv:type="Date">
      <sv:value>2006-05-01T21:46:25.697+02:00</sv:value>
    </sv:property>
    <sv:property sv:name="mgnl:activatorid" sv:type="String">
      <sv:value>superuser</sv:value>
    </sv:property>
    <sv:property sv:name="mgnl:Data" sv:type="String">
      <sv:value>MetaData</sv:value>
    </sv:property>
    <sv:property sv:name="mgnl:activated" sv:type="Boolean">
      <sv:value>false</sv:value>
    </sv:property>
  </sv:node>
  <sv:node sv:name="tab0">
    <sv:property sv:name="jcr:primaryType" sv:type="Name">
      <sv:value>mgnl:contentNode</sv:value>
    </sv:property>
    <sv:property sv:name="jcr:mixinTypes" sv:type="Name">
      <sv:value>mix:versionable</sv:value>
    </sv:property>
    <sv:property sv:name="jcr:uuid" sv:type="String">
      <sv:value>cd72e8d8-a69d-4661-9655-c0e1328b244a</sv:value>
    </sv:property>
    <sv:property sv:name="label" sv:type="String">
      <sv:value>dialog.devShow.include.tab0.label</sv:value>
    </sv:property>
    <sv:property sv:name="controlType" sv:type="String">
      <sv:value>tab</sv:value>
    </sv:property>
    <sv:node sv:name="MetaData">
      <sv:property sv:name="jcr:primaryType" sv:type="Name">
        <sv:value>mgnl:metaData</sv:value>
      </sv:property>
      <sv:property sv:name="mgnl:authorid" sv:type="String">
        <sv:value>superuser</sv:value>
      </sv:property>
      <sv:property sv:name="mgnl:creationdate" sv:type="String">
        <sv:value>2004-11-02T15:34:29.590+01:00</sv:value>
      </sv:property>
      <sv:property sv:name="mgnl:lastaction" sv:type="Date">
        <sv:value>2006-05-01T21:46:25.677+02:00</sv:value>
      </sv:property>
      <sv:property sv:name="mgnl:lastmodified" sv:type="String">
        <sv:value>2005-04-04T15:11:47.540+02:00</sv:value>
      </sv:property>
      <sv:property sv:name="mgnl:activatorid" sv:type="String">
        <sv:value>superuser</sv:value>
      </sv:property>
      <sv:property sv:name="mgnl:Data" sv:type="String">
        <sv:value>MetaData</sv:value>
      </sv:property>
      <sv:property sv:name="mgnl:activated" sv:type="Boolean">
        <sv:value>false</sv:value>
      </sv:property>
    </sv:node>
    <sv:node sv:name="color1">
      <sv:property sv:name="jcr:primaryType" sv:type="Name">
        <sv:value>mgnl:contentNode</sv:value>
      </sv:property>
      <sv:property sv:name="jcr:mixinTypes" sv:type="Name">
        <sv:value>mix:versionable</sv:value>
      </sv:property>
      <sv:property sv:name="jcr:uuid" sv:type="String">
        <sv:value>39e2f6a5-cfd0-4391-904a-47c8d4d0b1f8</sv:value>
      </sv:property>
      <sv:property sv:name="description" sv:type="String">
        <sv:value>dialog.devShow.include.tab0.color1.description</sv:value>
      </sv:property>
      <sv:property sv:name="type" sv:type="String">
        <sv:value>String</sv:value>
      </sv:property>
      <sv:property sv:name="colorStart" sv:type="String">
        <sv:value>00ff00</sv:value>
      </sv:property>
      <sv:property sv:name="colorOffset" sv:type="String">
        <sv:value>003300</sv:value>
      </sv:property>
      <sv:property sv:name="file" sv:type="String">
        <sv:value>/templates/jsp/samples/templateDevShow/dialogIncludes/colorSelector.jsp</sv:value>
      </sv:property>
      <sv:property sv:name="label" sv:type="String">
        <sv:value>dialog.devShow.include.tab0.color1.label</sv:value>
      </sv:property>
      <sv:property sv:name="controlType" sv:type="String">
        <sv:value>include</sv:value>
      </sv:property>
      <sv:node sv:name="MetaData">
        <sv:property sv:name="jcr:primaryType" sv:type="Name">
          <sv:value>mgnl:metaData</sv:value>
        </sv:property>
        <sv:property sv:name="mgnl:authorid" sv:type="String">
          <sv:value>superuser</sv:value>
        </sv:property>
        <sv:property sv:name="mgnl:creationdate" sv:type="String">
          <sv:value>2004-11-02T15:34:29.732+01:00</sv:value>
        </sv:property>
        <sv:property sv:name="mgnl:lastaction" sv:type="Date">
          <sv:value>2006-05-01T21:46:25.677+02:00</sv:value>
        </sv:property>
        <sv:property sv:name="mgnl:lastmodified" sv:type="String">
          <sv:value>2005-04-04T15:12:05.425+02:00</sv:value>
        </sv:property>
        <sv:property sv:name="mgnl:activatorid" sv:type="String">
          <sv:value>superuser</sv:value>
        </sv:property>
        <sv:property sv:name="mgnl:Data" sv:type="String">
          <sv:value>MetaData</sv:value>
        </sv:property>
        <sv:property sv:name="mgnl:activated" sv:type="Boolean">
          <sv:value>false</sv:value>
        </sv:property>
      </sv:node>
    </sv:node>
    <sv:node sv:name="color2">
      <sv:property sv:name="jcr:primaryType" sv:type="Name">
        <sv:value>mgnl:contentNode</sv:value>
      </sv:property>
      <sv:property sv:name="jcr:mixinTypes" sv:type="Name">
        <sv:value>mix:versionable</sv:value>
      </sv:property>
      <sv:property sv:name="jcr:uuid" sv:type="String">
        <sv:value>7b9251e6-68ae-42c4-829b-9358c637ddae</sv:value>
      </sv:property>
      <sv:property sv:name="description" sv:type="String">
        <sv:value>dialog.devShow.include.tab0.color2.description</sv:value>
      </sv:property>
      <sv:property sv:name="type" sv:type="String">
        <sv:value>String</sv:value>
      </sv:property>
      <sv:property sv:name="colorStart" sv:type="String">
        <sv:value>ff0000</sv:value>
      </sv:property>
      <sv:property sv:name="colorOffset" sv:type="String">
        <sv:value>330000</sv:value>
      </sv:property>
      <sv:property sv:name="file" sv:type="String">
        <sv:value>/templates/jsp/samples/templateDevShow/dialogIncludes/colorSelector.jsp</sv:value>
      </sv:property>
      <sv:property sv:name="label" sv:type="String">
        <sv:value>dialog.devShow.include.tab0.color2.label</sv:value>
      </sv:property>
      <sv:property sv:name="controlType" sv:type="String">
        <sv:value>include</sv:value>
      </sv:property>
      <sv:node sv:name="MetaData">
        <sv:property sv:name="jcr:primaryType" sv:type="Name">
          <sv:value>mgnl:metaData</sv:value>
        </sv:property>
        <sv:property sv:name="mgnl:authorid" sv:type="String">
          <sv:value>superuser</sv:value>
        </sv:property>
        <sv:property sv:name="mgnl:creationdate" sv:type="String">
          <sv:value>2004-11-02T15:34:29.801+01:00</sv:value>
        </sv:property>
        <sv:property sv:name="mgnl:lastaction" sv:type="Date">
          <sv:value>2006-05-01T21:46:25.677+02:00</sv:value>
        </sv:property>
        <sv:property sv:name="mgnl:lastmodified" sv:type="String">
          <sv:value>2005-04-04T15:12:26.677+02:00</sv:value>
        </sv:property>
        <sv:property sv:name="mgnl:activatorid" sv:type="String">
          <sv:value>superuser</sv:value>
        </sv:property>
        <sv:property sv:name="mgnl:Data" sv:type="String">
          <sv:value>MetaData</sv:value>
        </sv:property>
        <sv:property sv:name="mgnl:activated" sv:type="Boolean">
          <sv:value>false</sv:value>
        </sv:property>
      </sv:node>
    </sv:node>
  </sv:node>
</sv:node>
